dependency_scanner_tool/__init__.py
dependency_scanner_tool/__main__.py
dependency_scanner_tool/api_categorization.py
dependency_scanner_tool/api_example.py
dependency_scanner_tool/categorization.py
dependency_scanner_tool/cli.py
dependency_scanner_tool/exceptions.py
dependency_scanner_tool/file_type_detector.py
dependency_scanner_tool/file_utils.py
dependency_scanner_tool/html_report.py
dependency_scanner_tool/scanner.py
dependency_scanner_tool/analyzers/__init__.py
dependency_scanner_tool/analyzers/analyzer_manager.py
dependency_scanner_tool/analyzers/base.py
dependency_scanner_tool/analyzers/java_analyzer.py
dependency_scanner_tool/analyzers/python_analyzer.py
dependency_scanner_tool/analyzers/scala_analyzer.py
dependency_scanner_tool/api_analyzers/__init__.py
dependency_scanner_tool/api_analyzers/base.py
dependency_scanner_tool/api_analyzers/python_api_analyzer.py
dependency_scanner_tool/api_analyzers/registry.py
dependency_scanner_tool/api_analyzers/scala_api_analyzer.py
dependency_scanner_tool/normalizers/__init__.py
dependency_scanner_tool/normalizers/java_package.py
dependency_scanner_tool/normalizers/python_package.py
dependency_scanner_tool/parsers/__init__.py
dependency_scanner_tool/parsers/base.py
dependency_scanner_tool/parsers/build_sbt.py
dependency_scanner_tool/parsers/conda_environment.py
dependency_scanner_tool/parsers/gradle_build.py
dependency_scanner_tool/parsers/maven_pom.py
dependency_scanner_tool/parsers/parser_manager.py
dependency_scanner_tool/parsers/pip_dependencies.py
dependency_scanner_tool/parsers/pyproject_toml.py
dependency_scanner_tool/parsers/requirements_txt.py
dependency_scanner_tool/reporters/__init__.py
dependency_scanner_tool/reporters/html_reporter.py
dependency_scanner_tool/reporters/json_reporter.py
dependency_scanner_tool/reporters/templates/report.html
dependency_scanner_tool_2-0.1.3.dist-info/METADATA
dependency_scanner_tool_2-0.1.3.dist-info/WHEEL
dependency_scanner_tool_2-0.1.3.dist-info/entry_points.txt
dependency_scanner_tool_2-0.1.3.dist-info/RECORD
